arges
