Metadata-Version: 1.0
Name: arges
Version: 0.1
Summary: Automated testing
Home-page: UNKNOWN
Author: UNKNOWN
Author-email: UNKNOWN
License: UNKNOWN
Platform: UNKNOWN
